pyusbio/__init__.py
pyusbio/usbio_config.py
pyusbio-0.1.3.dist-info/entry_points.txt
pyusbio-0.1.3.dist-info/LICENSE
pyusbio-0.1.3.dist-info/WHEEL
pyusbio-0.1.3.dist-info/METADATA
pyusbio-0.1.3.dist-info/RECORD
