Metadata-Version: 2.1
Name: pyusbio
Version: 0.1.3
Summary: USB-IO2 control library for Python
Home-page: https://github.com/yukkeorg
License: MIT
Author: Yusuke Ohshima
Author-email: ohshima.yusuke@yukke.org
Requires-Python: >=3.6,<4.0
Classifier: License :: OSI Approved :: MIT License
Classifier: Programming Language :: Python :: 3
Classifier: Programming Language :: Python :: 3.6
Classifier: Programming Language :: Python :: 3.7
Classifier: Programming Language :: Python :: 3.8
Classifier: Programming Language :: Python :: 3.9
Requires-Dist: pyusb (>=1.1.0,<2.0.0)
Project-URL: Repository, https://github.com/yukkeorg/pyusbio
